CONTRIBUTING.rst
LICENSE
MANIFEST.in
README.rst
setup.cfg
setup.py
ring_doorbell/__init__.py
ring_doorbell/auth.py
ring_doorbell/chime.py
ring_doorbell/const.py
ring_doorbell/doorbot.py
ring_doorbell/generic.py
ring_doorbell/group.py
ring_doorbell/other.py
ring_doorbell/stickup_cam.py
ring_doorbell_intercom.egg-info/PKG-INFO
ring_doorbell_intercom.egg-info/SOURCES.txt
ring_doorbell_intercom.egg-info/dependency_links.txt
ring_doorbell_intercom.egg-info/requires.txt
ring_doorbell_intercom.egg-info/top_level.txt
tests/__init__.py
tests/helpers.py
tests/test_ring.py
tests/fixtures/ring_chime_health_attrs.json
tests/fixtures/ring_devices.json
tests/fixtures/ring_ding_active.json
tests/fixtures/ring_doorboot_health_attrs.json
tests/fixtures/ring_doorboot_health_attrs_id987653.json
tests/fixtures/ring_doorbots.json
tests/fixtures/ring_group_devices.json
tests/fixtures/ring_groups.json
tests/fixtures/ring_oauth.json
tests/fixtures/ring_session.json