Metadata-Version: 2.1
Name: ring-doorbell-intercom
Version: 0.7.3
Summary: A Python library to communicate with Ring Door Bell (https://ring.com/)
Home-page: https://github.com/michael-oknov/python-ring-doorbell
Author: Michael Oknov
Author-email: michael.oknov@gmail.com
License: LGPLv3+
Keywords: ring,door bell,home automation
Classifier: Environment :: Other Environment
Classifier: Intended Audience :: Developers
Classifier: License :: OSI Approved :: GNU Lesser General Public License v3 or later (LGPLv3+)
Classifier: Operating System :: OS Independent
Classifier: Programming Language :: Python
Classifier: Programming Language :: Python :: 3.6
Classifier: Programming Language :: Python :: 3.7
Classifier: Topic :: Home Automation
Classifier: Topic :: Software Development :: Libraries :: Python Modules
License-File: LICENSE
